ks_domain_tagger/__init__.py
ks_domain_tagger/judge.py
ks_domain_tagger/keywords.py
ks_domain_tagger/knowledgebase.py
ks_domain_tagger/paragraphs.py
ks_domain_tagger/rater.py
ks_domain_tagger-0.1.0.dist-info/licenses/LICENSE
ks_domain_tagger-0.1.0.dist-info/METADATA
ks_domain_tagger-0.1.0.dist-info/WHEEL
ks_domain_tagger-0.1.0.dist-info/top_level.txt
ks_domain_tagger-0.1.0.dist-info/RECORD
