Metadata-Version: 2.4
Name: ks-domain-tagger
Version: 0.1.0
Summary: A tool to find relevant Wikipedia articles for a given paragraph and score them.
Home-page: https://github.com/C-you-know/Domain-Tagging-and-Generation
Author: Chinmay J S
Author-email: Chinmay.you.know@gmail.com
Classifier: Programming Language :: Python :: 3
Classifier: License :: OSI Approved :: MIT License
Classifier: Operating System :: OS Independent
Requires-Python: >=3.7
License-File: LICENSE
Requires-Dist: nltk>=3.6
Requires-Dist: scikit-learn>=1.0
Requires-Dist: requests>=2.25
Requires-Dist: beautifulsoup4>=4.9
Requires-Dist: rapidfuzz>=1.8
Requires-Dist: numpy>=1.20
Requires-Dist: termcolor>=1.1.0
Dynamic: author
Dynamic: author-email
Dynamic: classifier
Dynamic: description
Dynamic: description-content-type
Dynamic: home-page
Dynamic: license-file
Dynamic: requires-dist
Dynamic: requires-python
Dynamic: summary
